[
  {
    "lat": 34.697099,
    "lng": 113.545101
  },
  {
    "lat": 34.695688,
    "lng": 113.566724
  },
  {
    "lat": 34.700062,
    "lng": 113.577364
  },
  {
    "lat": 34.699780,
    "lng": 113.593151
  },
  {
    "lat": 34.698895,
    "lng": 113.594660
  },
  {
    "lat": 34.663182,
    "lng": 113.606513
  },
  {
    "lat": 34.662354,
    "lng": 113.593932
  },
  {
    "lat": 34.643311,
    "lng": 113.594723
  },
  {
    "lat": 34.645145,
    "lng": 113.587677
  },
  {
    "lat": 34.646150,
    "lng": 113.578403
  },
  {
    "lat": 34.646682,
    "lng": 113.562658
  },
  {
    "lat": 34.649426,
    "lng": 113.554534
  },
  {
    "lat": 34.654491,
    "lng": 113.543193
  },
  {
    "lat": 34.663109,
    "lng": 113.526667
  },
  {
    "lat": 34.671992,
    "lng": 113.517918
  },
  {
    "lat": 34.677411,
    "lng": 113.522455
  },
  {
    "lat": 34.689757,
    "lng": 113.536496
  },
  {
    "lat": 34.698016,
    "lng": 113.542761
  }
]